quickex_sdk/__about__.py
quickex_sdk/__init__.py
quickex_sdk/client.py
quickex_sdk/models.py
quickex_sdk/sdk.py
quickex_sdk-1.0.11.dist-info/METADATA
quickex_sdk-1.0.11.dist-info/WHEEL
quickex_sdk-1.0.11.dist-info/licenses/LICENSE.txt
quickex_sdk-1.0.11.dist-info/RECORD
